napari_sim_processor/__init__.py
napari_sim_processor/_sim_widget.py
napari_sim_processor/_version.py
napari_sim_processor/napari.yaml
napari_sim_processor/widget_settings.py
napari_sim_processor/_tests/__init__.py
napari_sim_processor/_tests/test_widget.py
napari_sim_processor/processors/__init__.py
napari_sim_processor/processors/baseSimProcessor.py
napari_sim_processor/processors/baseSimProcessor3D.py
napari_sim_processor/processors/convSimProcessor.py
napari_sim_processor/processors/hexSimProcessor.py
napari_sim_processor/processors/raSimProcessor.py
napari_sim_processor/processors/simProcessor.py
napari_sim_processor-0.1.1.dist-info/LICENSE
napari_sim_processor-0.1.1.dist-info/METADATA
napari_sim_processor-0.1.1.dist-info/WHEEL
napari_sim_processor-0.1.1.dist-info/entry_points.txt
napari_sim_processor-0.1.1.dist-info/top_level.txt
napari_sim_processor-0.1.1.dist-info/RECORD
