Metadata-Version: 2.1
Name: napari-sim-processor
Version: 0.1.1
Summary: A plugin to process Structured Illumination Microscopy data with gpu acceleration
Home-page: https://github.com/andreabassi78/napari-sim-processor
Author: Andrea Bassi and Mark Neil
Author-email: andrea1.bassi@polimi.it
License: BSD-3-Clause
Project-URL: Bug Tracker, https://github.com/andreabassi78/napari-sim-processor/issues
Project-URL: Documentation, https://github.com/andreabassi78/napari-sim-processor#README.md
Project-URL: Source Code, https://github.com/andreabassi78/napari-sim-processor
Project-URL: User Support, https://github.com/andreabassi78/napari-sim-processor/issues
Classifier: Development Status :: 2 - Pre-Alpha
Classifier: Intended Audience :: Developers
Classifier: Framework :: napari
Classifier: Topic :: Software Development :: Testing
Classifier: Programming Language :: Python
Classifier: Programming Language :: Python :: 3
Classifier: Programming Language :: Python :: 3.8
Classifier: Programming Language :: Python :: 3.9
Classifier: Programming Language :: Python :: 3.10
Classifier: Operating System :: OS Independent
Classifier: License :: OSI Approved :: BSD License
Requires-Python: >=3.8
License-File: LICENSE
Requires-Dist: numpy
Requires-Dist: scipy
Requires-Dist: magicgui
Requires-Dist: qtpy
Requires-Dist: matplotlib
Requires-Dist: superqt >=0.3.2
Provides-Extra: testing
Requires-Dist: tox ; extra == 'testing'
Requires-Dist: pytest ; extra == 'testing'
Requires-Dist: pytest-cov ; extra == 'testing'
Requires-Dist: pytest-qt ; extra == 'testing'
Requires-Dist: napari ; extra == 'testing'
Requires-Dist: pyqt5 ; extra == 'testing'
Requires-Dist: matplotlib ; extra == 'testing'
Requires-Dist: numpy ; extra == 'testing'
Requires-Dist: scipy ; extra == 'testing'
Requires-Dist: superqt ; extra == 'testing'
